[{"state":{"code":"sequenceDiagram\n    participant user as Usuário\n    participant browser as Navegador\n    participant server as Servidor\n\n    user->>browser: Digita uma nova nota no campo de texto\n    browser->>user: Exibe a nota digitada\n\n    user->>browser: Clica no botão \"Submit\"\n    browser->>server: POST https://studies.cs.helsinki.fi/exampleapp/notes\n    Note right of server: O servidor processa a nova nota\n    activate server\n    server-->>browser: Confirmação da criação da nota\n    deactivate server\n\n    browser->>browser: Atualiza a lista de notas\n    browser->>server: GET https://studies.cs.helsinki.fi/exampleapp/data.json\n    activate server\n    server-->>browser: [{ \"content\": \"Nova nota\", \"date\": \"2023-1-1\" }, ... ]\n    deactivate server\n\n    browser->>user: Exibe a nova nota na lista\n  ","mermaid":"{\n  \"theme\": \"default\"\n}","autoSync":true,"rough":false,"updateDiagram":true,"panZoom":false},"time":1726010672983,"type":"auto","id":"cafb5e44-72e8-4190-8fe7-e785db5e5bdb","name":"curved-forest"}]